getgit/args.py
getgit/cli.py
getgit/clone.py
getgit/config.py
getgit/main.py
getgit/parse.py
getgit/wwyaml.py
getgit/__pycache__/args.cpython-310.pyc
getgit/__pycache__/cli.cpython-310.pyc
getgit/__pycache__/clone.cpython-310.pyc
getgit/__pycache__/config.cpython-310.pyc
getgit/__pycache__/main.cpython-310.pyc
getgit/__pycache__/parse.cpython-310.pyc
getgit/__pycache__/wwyaml.cpython-310.pyc
getgit/config/parse.yaml
getgit-0.1.8.dist-info/METADATA
getgit-0.1.8.dist-info/WHEEL
getgit-0.1.8.dist-info/entry_points.txt
getgit-0.1.8.dist-info/top_level.txt
getgit-0.1.8.dist-info/RECORD
