Metadata-Version: 2.1
Name: getgit
Version: 0.1.8
Summary: Cloning repositories of user
Home-page: https://github.com/kra53n/getgit
Author: Gregory Bakhtin
Author-email: greasha46@gmail.com
License: GPL3
Platform: UNKNOWN
Classifier: Topic :: Software Development :: Version Control :: Git
Classifier: Topic :: Utilities
Classifier: License :: OSI Approved :: GNU General Public License v3 (GPLv3)
Classifier: Programming Language :: Python :: 3
Classifier: Operating System :: POSIX :: Linux
Classifier: Operating System :: MacOS
Classifier: Operating System :: Microsoft :: Windows
Classifier: Environment :: Console
License-File: LICENSE
